{
  "config": {
    "configFile": "/home/runner/work/playwright-tests/playwright-tests/playwright.config.ts",
    "rootDir": "/home/runner/work/playwright-tests/playwright-tests/tests",
    "forbidOnly": true,
    "fullyParallel": true,
    "globalSetup": null,
    "globalTeardown": null,
    "globalTimeout": 0,
    "grep": {},
    "grepInvert": null,
    "maxFailures": 0,
    "metadata": {
      "ci": {
        "commitHref": "https://github.com/AHP15/playwright-tests/commit/b7e56104cd9591d1ebb3b47c8bbbab6536e84313",
        "commitHash": "b7e56104cd9591d1ebb3b47c8bbbab6536e84313",
        "buildHref": "https://github.com/AHP15/playwright-tests/actions/runs/14880993453"
      },
      "gitCommit": {
        "shortHash": "b7e5610",
        "hash": "b7e56104cd9591d1ebb3b47c8bbbab6536e84313",
        "subject": "Merge pull request #6 from AHP15/branch-3",
        "body": "Merge pull request #6 from AHP15/branch-3\n\nGenerate Comment summary",
        "author": {
          "name": "Abdessittir Harkati",
          "email": "harkati.web.dev@gmail.com",
          "time": 1746613293000
        },
        "committer": {
          "name": "GitHub",
          "email": "noreply@github.com",
          "time": 1746613293000
        },
        "branch": "main"
      },
      "actualWorkers": 1
    },
    "preserveOutput": "always",
    "reporter": [
      [
        "html",
        null
      ],
      [
        "json",
        {
          "outputFile": "playwright-report/results.json"
        }
      ]
    ],
    "reportSlowTests": {
      "max": 5,
      "threshold": 300000
    },
    "quiet": false,
    "projects": [
      {
        "outputDir": "/home/runner/work/playwright-tests/playwright-tests/test-results",
        "repeatEach": 1,
        "retries": 2,
        "metadata": {
          "ci": {
            "commitHref": "https://github.com/AHP15/playwright-tests/commit/b7e56104cd9591d1ebb3b47c8bbbab6536e84313",
            "commitHash": "b7e56104cd9591d1ebb3b47c8bbbab6536e84313",
            "buildHref": "https://github.com/AHP15/playwright-tests/actions/runs/14880993453"
          },
          "gitCommit": {
            "shortHash": "b7e5610",
            "hash": "b7e56104cd9591d1ebb3b47c8bbbab6536e84313",
            "subject": "Merge pull request #6 from AHP15/branch-3",
            "body": "Merge pull request #6 from AHP15/branch-3\n\nGenerate Comment summary",
            "author": {
              "name": "Abdessittir Harkati",
              "email": "harkati.web.dev@gmail.com",
              "time": 1746613293000
            },
            "committer": {
              "name": "GitHub",
              "email": "noreply@github.com",
              "time": 1746613293000
            },
            "branch": "main"
          },
          "actualWorkers": 1
        },
        "id": "chromium",
        "name": "chromium",
        "testDir": "/home/runner/work/playwright-tests/playwright-tests/tests",
        "testIgnore": [],
        "testMatch": [
          "**/*.@(spec|test).?(c|m)[jt]s?(x)"
        ],
        "timeout": 30000
      }
    ],
    "shard": null,
    "updateSnapshots": "missing",
    "updateSourceMethod": "patch",
    "version": "1.52.0",
    "workers": 1,
    "webServer": null
  },
  "suites": [
    {
      "title": "example.spec.ts",
      "file": "example.spec.ts",
      "column": 0,
      "line": 0,
      "specs": [
        {
          "title": "has title",
          "ok": true,
          "tags": [],
          "tests": [
            {
              "timeout": 30000,
              "annotations": [],
              "expectedStatus": "passed",
              "projectId": "chromium",
              "projectName": "chromium",
              "results": [
                {
                  "workerIndex": 0,
                  "parallelIndex": 0,
                  "status": "passed",
                  "duration": 1160,
                  "errors": [],
                  "stdout": [],
                  "stderr": [],
                  "retry": 0,
                  "startTime": "2025-05-07T10:23:11.800Z",
                  "annotations": [],
                  "attachments": []
                }
              ],
              "status": "expected"
            }
          ],
          "id": "a30a6eba6312f6b87ea5-b06063a3e613764d08f8",
          "file": "example.spec.ts",
          "line": 3,
          "column": 1
        },
        {
          "title": "get started link",
          "ok": true,
          "tags": [],
          "tests": [
            {
              "timeout": 30000,
              "annotations": [],
              "expectedStatus": "passed",
              "projectId": "chromium",
              "projectName": "chromium",
              "results": [
                {
                  "workerIndex": 0,
                  "parallelIndex": 0,
                  "status": "passed",
                  "duration": 593,
                  "errors": [],
                  "stdout": [],
                  "stderr": [],
                  "retry": 0,
                  "startTime": "2025-05-07T10:23:19.750Z",
                  "annotations": [],
                  "attachments": []
                }
              ],
              "status": "expected"
            }
          ],
          "id": "a30a6eba6312f6b87ea5-274e97907a6e3638a22f",
          "file": "example.spec.ts",
          "line": 10,
          "column": 1
        },
        {
          "title": "Should fail",
          "ok": false,
          "tags": [],
          "tests": [
            {
              "timeout": 30000,
              "annotations": [],
              "expectedStatus": "passed",
              "projectId": "chromium",
              "projectName": "chromium",
              "results": [
                {
                  "workerIndex": 0,
                  "parallelIndex": 0,
                  "status": "failed",
                  "duration": 3,
                  "error": {
                    "message": "Error: \u001b[2mexpect(\u001b[22m\u001b[31mreceived\u001b[39m\u001b[2m).\u001b[22mtoBe\u001b[2m(\u001b[22m\u001b[32mexpected\u001b[39m\u001b[2m) // Object.is equality\u001b[22m\n\nExpected: \u001b[32mfalse\u001b[39m\nReceived: \u001b[31mtrue\u001b[39m",
                    "stack": "Error: \u001b[2mexpect(\u001b[22m\u001b[31mreceived\u001b[39m\u001b[2m).\u001b[22mtoBe\u001b[2m(\u001b[22m\u001b[32mexpected\u001b[39m\u001b[2m) // Object.is equality\u001b[22m\n\nExpected: \u001b[32mfalse\u001b[39m\nReceived: \u001b[31mtrue\u001b[39m\n    at /home/runner/work/playwright-tests/playwright-tests/tests/example.spec.ts:21:16",
                    "location": {
                      "file": "/home/runner/work/playwright-tests/playwright-tests/tests/example.spec.ts",
                      "column": 16,
                      "line": 21
                    },
                    "snippet": "\u001b[0m \u001b[90m 19 |\u001b[39m\n \u001b[90m 20 |\u001b[39m test(\u001b[32m'Should fail'\u001b[39m\u001b[33m,\u001b[39m \u001b[36masync\u001b[39m ({}) \u001b[33m=>\u001b[39m {\n\u001b[31m\u001b[1m>\u001b[22m\u001b[39m\u001b[90m 21 |\u001b[39m   expect(\u001b[36mtrue\u001b[39m)\u001b[33m.\u001b[39mtoBe(\u001b[36mfalse\u001b[39m)\u001b[33m;\u001b[39m\n \u001b[90m    |\u001b[39m                \u001b[31m\u001b[1m^\u001b[22m\u001b[39m\n \u001b[90m 22 |\u001b[39m })\n \u001b[90m 23 |\u001b[39m\u001b[0m"
                  },
                  "errors": [
                    {
                      "location": {
                        "file": "/home/runner/work/playwright-tests/playwright-tests/tests/example.spec.ts",
                        "column": 16,
                        "line": 21
                      },
                      "message": "Error: \u001b[2mexpect(\u001b[22m\u001b[31mreceived\u001b[39m\u001b[2m).\u001b[22mtoBe\u001b[2m(\u001b[22m\u001b[32mexpected\u001b[39m\u001b[2m) // Object.is equality\u001b[22m\n\nExpected: \u001b[32mfalse\u001b[39m\nReceived: \u001b[31mtrue\u001b[39m\n\n  19 |\n  20 | test('Should fail', async ({}) => {\n> 21 |   expect(true).toBe(false);\n     |                ^\n  22 | })\n  23 |\n    at /home/runner/work/playwright-tests/playwright-tests/tests/example.spec.ts:21:16"
                    }
                  ],
                  "stdout": [],
                  "stderr": [],
                  "retry": 0,
                  "startTime": "2025-05-07T10:23:20.349Z",
                  "annotations": [],
                  "attachments": [
                    {
                      "name": "_error-context-0",
                      "contentType": "text/markdown",
                      "path": "/home/runner/work/playwright-tests/playwright-tests/test-results/example-Should-fail-chromium/error-context.md"
                    }
                  ],
                  "errorLocation": {
                    "file": "/home/runner/work/playwright-tests/playwright-tests/tests/example.spec.ts",
                    "column": 16,
                    "line": 21
                  }
                },
                {
                  "workerIndex": 1,
                  "parallelIndex": 0,
                  "status": "failed",
                  "duration": 9,
                  "error": {
                    "message": "Error: \u001b[2mexpect(\u001b[22m\u001b[31mreceived\u001b[39m\u001b[2m).\u001b[22mtoBe\u001b[2m(\u001b[22m\u001b[32mexpected\u001b[39m\u001b[2m) // Object.is equality\u001b[22m\n\nExpected: \u001b[32mfalse\u001b[39m\nReceived: \u001b[31mtrue\u001b[39m",
                    "stack": "Error: \u001b[2mexpect(\u001b[22m\u001b[31mreceived\u001b[39m\u001b[2m).\u001b[22mtoBe\u001b[2m(\u001b[22m\u001b[32mexpected\u001b[39m\u001b[2m) // Object.is equality\u001b[22m\n\nExpected: \u001b[32mfalse\u001b[39m\nReceived: \u001b[31mtrue\u001b[39m\n    at /home/runner/work/playwright-tests/playwright-tests/tests/example.spec.ts:21:16",
                    "location": {
                      "file": "/home/runner/work/playwright-tests/playwright-tests/tests/example.spec.ts",
                      "column": 16,
                      "line": 21
                    },
                    "snippet": "\u001b[0m \u001b[90m 19 |\u001b[39m\n \u001b[90m 20 |\u001b[39m test(\u001b[32m'Should fail'\u001b[39m\u001b[33m,\u001b[39m \u001b[36masync\u001b[39m ({}) \u001b[33m=>\u001b[39m {\n\u001b[31m\u001b[1m>\u001b[22m\u001b[39m\u001b[90m 21 |\u001b[39m   expect(\u001b[36mtrue\u001b[39m)\u001b[33m.\u001b[39mtoBe(\u001b[36mfalse\u001b[39m)\u001b[33m;\u001b[39m\n \u001b[90m    |\u001b[39m                \u001b[31m\u001b[1m^\u001b[22m\u001b[39m\n \u001b[90m 22 |\u001b[39m })\n \u001b[90m 23 |\u001b[39m\u001b[0m"
                  },
                  "errors": [
                    {
                      "location": {
                        "file": "/home/runner/work/playwright-tests/playwright-tests/tests/example.spec.ts",
                        "column": 16,
                        "line": 21
                      },
                      "message": "Error: \u001b[2mexpect(\u001b[22m\u001b[31mreceived\u001b[39m\u001b[2m).\u001b[22mtoBe\u001b[2m(\u001b[22m\u001b[32mexpected\u001b[39m\u001b[2m) // Object.is equality\u001b[22m\n\nExpected: \u001b[32mfalse\u001b[39m\nReceived: \u001b[31mtrue\u001b[39m\n\n  19 |\n  20 | test('Should fail', async ({}) => {\n> 21 |   expect(true).toBe(false);\n     |                ^\n  22 | })\n  23 |\n    at /home/runner/work/playwright-tests/playwright-tests/tests/example.spec.ts:21:16"
                    }
                  ],
                  "stdout": [],
                  "stderr": [],
                  "retry": 1,
                  "startTime": "2025-05-07T10:23:21.348Z",
                  "annotations": [],
                  "attachments": [
                    {
                      "name": "_error-context-0",
                      "contentType": "text/markdown",
                      "path": "/home/runner/work/playwright-tests/playwright-tests/test-results/example-Should-fail-chromium-retry1/error-context.md"
                    },
                    {
                      "name": "trace",
                      "contentType": "application/zip",
                      "path": "/home/runner/work/playwright-tests/playwright-tests/test-results/example-Should-fail-chromium-retry1/trace.zip"
                    }
                  ],
                  "errorLocation": {
                    "file": "/home/runner/work/playwright-tests/playwright-tests/tests/example.spec.ts",
                    "column": 16,
                    "line": 21
                  }
                },
                {
                  "workerIndex": 2,
                  "parallelIndex": 0,
                  "status": "failed",
                  "duration": 9,
                  "error": {
                    "message": "Error: \u001b[2mexpect(\u001b[22m\u001b[31mreceived\u001b[39m\u001b[2m).\u001b[22mtoBe\u001b[2m(\u001b[22m\u001b[32mexpected\u001b[39m\u001b[2m) // Object.is equality\u001b[22m\n\nExpected: \u001b[32mfalse\u001b[39m\nReceived: \u001b[31mtrue\u001b[39m",
                    "stack": "Error: \u001b[2mexpect(\u001b[22m\u001b[31mreceived\u001b[39m\u001b[2m).\u001b[22mtoBe\u001b[2m(\u001b[22m\u001b[32mexpected\u001b[39m\u001b[2m) // Object.is equality\u001b[22m\n\nExpected: \u001b[32mfalse\u001b[39m\nReceived: \u001b[31mtrue\u001b[39m\n    at /home/runner/work/playwright-tests/playwright-tests/tests/example.spec.ts:21:16",
                    "location": {
                      "file": "/home/runner/work/playwright-tests/playwright-tests/tests/example.spec.ts",
                      "column": 16,
                      "line": 21
                    },
                    "snippet": "\u001b[0m \u001b[90m 19 |\u001b[39m\n \u001b[90m 20 |\u001b[39m test(\u001b[32m'Should fail'\u001b[39m\u001b[33m,\u001b[39m \u001b[36masync\u001b[39m ({}) \u001b[33m=>\u001b[39m {\n\u001b[31m\u001b[1m>\u001b[22m\u001b[39m\u001b[90m 21 |\u001b[39m   expect(\u001b[36mtrue\u001b[39m)\u001b[33m.\u001b[39mtoBe(\u001b[36mfalse\u001b[39m)\u001b[33m;\u001b[39m\n \u001b[90m    |\u001b[39m                \u001b[31m\u001b[1m^\u001b[22m\u001b[39m\n \u001b[90m 22 |\u001b[39m })\n \u001b[90m 23 |\u001b[39m\u001b[0m"
                  },
                  "errors": [
                    {
                      "location": {
                        "file": "/home/runner/work/playwright-tests/playwright-tests/tests/example.spec.ts",
                        "column": 16,
                        "line": 21
                      },
                      "message": "Error: \u001b[2mexpect(\u001b[22m\u001b[31mreceived\u001b[39m\u001b[2m).\u001b[22mtoBe\u001b[2m(\u001b[22m\u001b[32mexpected\u001b[39m\u001b[2m) // Object.is equality\u001b[22m\n\nExpected: \u001b[32mfalse\u001b[39m\nReceived: \u001b[31mtrue\u001b[39m\n\n  19 |\n  20 | test('Should fail', async ({}) => {\n> 21 |   expect(true).toBe(false);\n     |                ^\n  22 | })\n  23 |\n    at /home/runner/work/playwright-tests/playwright-tests/tests/example.spec.ts:21:16"
                    }
                  ],
                  "stdout": [],
                  "stderr": [],
                  "retry": 2,
                  "startTime": "2025-05-07T10:23:22.063Z",
                  "annotations": [],
                  "attachments": [
                    {
                      "name": "_error-context-0",
                      "contentType": "text/markdown",
                      "path": "/home/runner/work/playwright-tests/playwright-tests/test-results/example-Should-fail-chromium-retry2/error-context.md"
                    }
                  ],
                  "errorLocation": {
                    "file": "/home/runner/work/playwright-tests/playwright-tests/tests/example.spec.ts",
                    "column": 16,
                    "line": 21
                  }
                }
              ],
              "status": "unexpected"
            }
          ],
          "id": "a30a6eba6312f6b87ea5-3ea5ca4fa83ba72684b3",
          "file": "example.spec.ts",
          "line": 20,
          "column": 1
        }
      ]
    }
  ],
  "errors": [],
  "stats": {
    "startTime": "2025-05-07T10:23:11.088Z",
    "duration": 11010.302,
    "expected": 2,
    "skipped": 0,
    "unexpected": 1,
    "flaky": 0
  }
}